deeptracer/__init__.py
deeptracer/model.py
deeptracer/utils.py
deeptracer/video_processor.py
deeptracer-0.1.3.dist-info/METADATA
deeptracer-0.1.3.dist-info/WHEEL
deeptracer-0.1.3.dist-info/top_level.txt
deeptracer-0.1.3.dist-info/RECORD
