Metadata-Version: 2.1
Name: deeptracer
Version: 0.1.3
Summary: A powerful tool for detecting and analyzing deepfake images and videos.
Author: Vishwa
Author-email: jvishu06@gmail.com
Classifier: Programming Language :: Python :: 3
Classifier: License :: OSI Approved :: MIT License
Classifier: Operating System :: OS Independent
Requires-Python: >=3.6
Requires-Dist: torch
Requires-Dist: facenet-pytorch
Requires-Dist: Pillow
Requires-Dist: opencv-python
Requires-Dist: numpy
Requires-Dist: gdown
